{
  "products": [
    {
      "name": "Soda Sifón 1L",
      "code": "S1L",
      "price": 150.0
    },
    {
      "name": "Agua Bidón 20L",
      "code": "A20L",
      "price": 800.0
    },
    {
      "name": "Agua Pack 1.5L x6",
      "code": "AP15",
      "price": 1200.0
    },
    {
      "name": "Gas Garrafa 10kg",
      "code": "G10",
      "price": 4500.0
    },
    {
      "name": "Dispenser Frio/Calor",
      "code": "DISP01",
      "price": 50000.0
    }
  ],
  "clients": [
    {
      "name": "Juan Perez",
      "address": "Av. San Martin 123",
      "phone": null,
      "balance": 0.0
    },
    {
      "name": "Restaurante El Pollito",
      "address": "Rivadavia 450",
      "phone": null,
      "balance": 0.0
    },
    {
      "name": "Maria Gonzalez",
      "address": "Belgrano 900",
      "phone": null,
      "balance": 0.0
    },
    {
      "name": "Franco Dell'Orsi",
      "address": "Feliciano Mazzieri",
      "phone": "3423234",
      "balance": 0.0
    },
    {
      "name": "Lara Salomón",
      "address": "Bv La Loma 7412",
      "phone": "3554543",
      "balance": 500.0
    },
    {
      "name": "Cliente Navegador Test",
      "address": "Calle Web 123",
      "phone": "999888777",
      "balance": 0.0
    }
  ]
}